<?xml version="1.0" encoding="UTF-8"?>
<panel layout="BorderLayout">
  <hbox constraints="BorderLayout.NORTH" border="EmptyBorder(5,5,5,5)">
    <button id="loadButton" text="Load Show or Template..." mnemonic="VK_L"
     action="load" />
    <button id="searchButton" text="Search Record Library" mnemonic="VK_S" 
     action="search" />
    <glue />
    <button id="helpButton" text="Help..." mnemonic="VK_H" 
     action="help" />
    <button id="feedbackButton" text="Feedback..." mnemonic="VK_F" 
     action="feedback" />
  </hbox>

  <panel layout="BorderLayout" constraints="BorderLayout.CENTER">
    <panel layout="BorderLayout" constraints="BorderLayout.NORTH">
      <subbanner text="Useful Tracks" 
       constraints="BorderLayout.NORTH" />
      <scrollpane id="binScrollPane"
       constraints="BorderLayout.CENTER">
        <panel id="binGroupPanel" />
      </scrollpane>
    </panel>
    <panel layout="BorderLayout" constraints="BorderLayout.CENTER">
      <subbanner text="Sound Channels" 
       constraints="BorderLayout.NORTH" />
      <scrollpane id="channelScrollPane"
       constraints="BorderLayout.CENTER">
        <panel id="channelGroupPanel" />
      </scrollpane>
    </panel>
    <panel layout="BorderLayout" constraints="BorderLayout.SOUTH">
      <subbanner text="Quick Notes"
       constraints="BorderLayout.NORTH" />
      <textarea id="noteArea" border="LoweredBevelBorder"
       text="Type quick notes here..." rows="3" />
    </panel>
  </panel>

  <hbox constraints="BorderLayout.SOUTH" border="EmptyBorder(5,5,5,5)">
    <hint text="For help, click the Help button." />
  </hbox>
</panel>
